{
  "title": "llama3_1_start",
  "content": "# llama3.1_start\n\nContent-Type: text/x-zim-wiki\nWiki-Format: zim 0.6\nCreation-Date: 2024-09-02T11:43:14-07:00\n\n====== llama3.1 start ======\npython3 -m venv llama-test-env\nsource llama-test-env/bin/activate\npip install torch transformers sentencepiece\npython ~/Repository/llama-models/models/llama3_1/llama.py --model instruct\n\n\n\n## Metadata\n- **Source**: All of it Anything Everything At Once/llama3.1_start.txt\n- **Type**: document\n- **Tags**: document, All_of_it_Anything_Everything_At_Once\n- **Imported**: 2025-05-05T16:25:37.147Z",
  "source": {
    "type": "notebook",
    "path": "All of it Anything Everything At Once/llama3.1_start.txt",
    "importedAt": "2025-05-05T16:25:37.147Z"
  },
  "created": "2025-05-05T16:25:37.147Z",
  "modified": "2025-05-05T16:25:37.147Z",
  "tags": [
    "document",
    "All_of_it_Anything_Everything_At_Once"
  ]
}